holidays_co/__init__.py
holidays_co-1.0.0.dist-info/LICENSE
holidays_co-1.0.0.dist-info/METADATA
holidays_co-1.0.0.dist-info/WHEEL
holidays_co-1.0.0.dist-info/top_level.txt
holidays_co-1.0.0.dist-info/RECORD
