Metadata-Version: 2.1
Name: holidays-co
Version: 1.0.0
Summary: Módulo de utilidades para festivos en Colombia
Home-page: https://github.com/jmejia32/holidays_co
Author: Javier Mejía
Author-email: jmjaviermejiaest@gmail.com
License: UNKNOWN
Platform: UNKNOWN
Classifier: Programming Language :: Python :: 3
Classifier: License :: OSI Approved :: MIT License
Classifier: Operating System :: OS Independent
